caribou_hi/__init__.py
caribou_hi/_version.py
caribou_hi/absorption_model.py
caribou_hi/absorption_physical_model.py
caribou_hi/emission_absorption_model.py
caribou_hi/emission_absorption_physical_model.py
caribou_hi/emission_model.py
caribou_hi/emission_physical_model.py
caribou_hi/hi_model.py
caribou_hi/hi_physical_model.py
caribou_hi/physics.py
caribou_hi-4.2.0.dist-info/licenses/LICENSE
caribou_hi-4.2.0.dist-info/METADATA
caribou_hi-4.2.0.dist-info/WHEEL
caribou_hi-4.2.0.dist-info/top_level.txt
caribou_hi-4.2.0.dist-info/RECORD
