Metadata-Version: 2.4
Name: caribou_hi
Version: 4.2.0
Summary: A Bayesian Model of the Diffuse Neutral Interstellar Medium
Home-page: https://github.com/tvwenger/caribou_hi
Author: Trey V. Wenger
Author-email: Trey Wenger <tvwenger@gmail.com>
License: The MIT License (MIT)
Project-URL: Homepage, https://github.com/tvwenger/caribou_hi
Classifier: Programming Language :: Python :: 3
Classifier: License :: OSI Approved :: GNU General Public License v3 (GPLv3)
Classifier: Operating System :: OS Independent
Requires-Python: >=3.11
License-File: LICENSE
Requires-Dist: bayes_spec>=1.9.0
Dynamic: author
Dynamic: home-page
Dynamic: license-file
Dynamic: requires-python
